lumberpy/__init__.py
lumberpy/cli.py
lumberpy/click.py
lumberpy/colored_formatter.py
lumberpy/config.py
lumberpy-0.1.0.dist-info/LICENSE
lumberpy-0.1.0.dist-info/METADATA
lumberpy-0.1.0.dist-info/WHEEL
lumberpy-0.1.0.dist-info/entry_points.txt
lumberpy-0.1.0.dist-info/top_level.txt
lumberpy-0.1.0.dist-info/RECORD
