Metadata-Version: 2.1
Name: lumberpy
Version: 0.1.0
Summary: Lumberpy is an easily configurable python3 module for advanced logging use cases
Home-page: https://gitlab.com/GreyRook/lumberpy
Author: Grey Rook GmbH
Author-email: f.elsner@greyrook.com
License: MIT license
Keywords: lumberpy
Platform: UNKNOWN
Classifier: Development Status :: 2 - Pre-Alpha
Classifier: Intended Audience :: Developers
Classifier: License :: OSI Approved :: MIT License
Classifier: Natural Language :: English
Classifier: Programming Language :: Python :: 3
Classifier: Programming Language :: Python :: 3.6
Classifier: Programming Language :: Python :: 3.7
Requires-Dist: Click (>=6.0)
Requires-Dist: coloredlogs (==10.0)
